main.py
evenity/__init__.py
evenity/observable.py
evenity/observer.py
evenity/plugins/__init__.py
evenity/plugins/ftp.py
evenity/plugins/kafka.py
evenity/plugins/shell.py
evenity/plugins/telegram.py
evenity/plugins/websocket.py
evenity-0.1.0.dist-info/LICENSE
evenity-0.1.0.dist-info/METADATA
evenity-0.1.0.dist-info/WHEEL
evenity-0.1.0.dist-info/top_level.txt
evenity-0.1.0.dist-info/RECORD
