Metadata-Version: 2.1
Name: evenity
Version: 0.1.0
Summary: Pluggable event hooks library
Author-email: Mario Baldi <mariobaldi.py@gmail.com>
Project-URL: Homepage, https://github.com/baldimario/evenity
Project-URL: Bug Tracker, https://github.com/baldimario/evenity/issues
Classifier: Programming Language :: Python :: 3
Classifier: Operating System :: OS Independent
Requires-Python: >=3.5
License-File: LICENSE
